main.py
main_export_header.py
main_metrics.py
main_threshold.py
a3d/__init__.py
a3d/accel.py
a3d/analog_lut.py
a3d/certificates.py
a3d/confidence.py
a3d/config.py
a3d/correlation_model.py
a3d/crossmodal_learner.py
a3d/decoder_bposd.py
a3d/decoder_greedy.py
a3d/decoder_ml.py
a3d/decoder_mwpm.py
a3d/decoder_mwpm_corr.py
a3d/decoder_mwpm_pipeline.py
a3d/decoder_mwpm_pm.py
a3d/decoder_unionfind.py
a3d/dem_export.py
a3d/export.py
a3d/graph.py
a3d/hardware_interface.py
a3d/layouts.py
a3d/leakage.py
a3d/llr_schema.py
a3d/logging_utils.py
a3d/metrics.py
a3d/noise_physical.py
a3d/research_validation.py
a3d/reweight_bp.py
a3d/reweight_transformer.py
a3d/reweight_transformer_sota.py
a3d/runtime.py
a3d/stats.py
a3d/stim_adapter.py
a3d/sweep.py
aegis_qec-1.0.23.dist-info/licenses/LICENSE
aegis_qec-1.0.23.dist-info/METADATA
aegis_qec-1.0.23.dist-info/WHEEL
aegis_qec-1.0.23.dist-info/entry_points.txt
aegis_qec-1.0.23.dist-info/top_level.txt
aegis_qec-1.0.23.dist-info/RECORD
