Metadata-Version: 2.4
Name: aegis-qec
Version: 1.0.23
Summary: Research-grade, hardware-aware QEC stack for surface codes.
Author: Hamid Bahri
License: MIT License
Project-URL: Homepage, https://github.com/hamidbahri92/Aegis
Classifier: Programming Language :: Python :: 3
Classifier: License :: OSI Approved :: MIT License
Classifier: Operating System :: OS Independent
Requires-Python: >=3.9
License-File: LICENSE
Requires-Dist: numpy>=1.21.0
Requires-Dist: networkx>=3.0
Requires-Dist: matplotlib>=3.5.0
Provides-Extra: full
Requires-Dist: pyarrow>=10.0.0; extra == "full"
Requires-Dist: pytest>=7.0.0; extra == "full"
Dynamic: license-file
